gs_sdk/ComputeProxy.py
gs_sdk/PWConfig.py
gs_sdk/__init__.py
gs_sdk/camera.py
gs_sdk/config.py
gs_sdk/consul_client.py
gs_sdk/main.py
gs_sdk/test_video.py
gs_sdk/test_video_sdk.py
gs_sdk-2.0.0.dist-info/METADATA
gs_sdk-2.0.0.dist-info/WHEEL
gs_sdk-2.0.0.dist-info/top_level.txt
gs_sdk-2.0.0.dist-info/RECORD
