Metadata-Version: 2.1
Name: gs-sdk
Version: 2.0.0
Summary: sdk调用
Home-page: http://forthink.xin:8889/dq/sdk.git
Author: duqiang
Author-email: 1427327705@qq.com
License: UNKNOWN
Platform: UNKNOWN
Requires-Python: >=3.9
Requires-Dist: python-consul (==1.1.0)
Requires-Dist: paho-mqtt (==1.6.1)
Requires-Dist: pydantic (==1.8.2)
